NESTML-8.2.0.data/data/doc/citing.rst
NESTML-8.2.0.data/data/doc/extending.rst
NESTML-8.2.0.data/data/doc/getting_help.rst
NESTML-8.2.0.data/data/doc/installation.rst
NESTML-8.2.0.data/data/doc/license.rst
NESTML-8.2.0.data/data/doc/requirements.txt
NESTML-8.2.0.data/data/doc/extending/Dimitri_Plotnikov_Doctoral_Thesis.pdf
NESTML-8.2.0.data/data/doc/extending/Konstantin_Perun_Master_thesis.pdf
NESTML-8.2.0.data/data/doc/extending/Tammo_Ippen_Master_Thesis.pdf
NESTML-8.2.0.data/data/doc/fig/Asymmetric-STDP-learning-window-Spike-timing-window-of-STDP-for-the-induction-of.png
NESTML-8.2.0.data/data/doc/fig/code_gen_opts.png
NESTML-8.2.0.data/data/doc/fig/code_gen_opts.svg
NESTML-8.2.0.data/data/doc/fig/fncom-04-00141-g003.jpg
NESTML-8.2.0.data/data/doc/fig/genn-logo-thumbnail.png
NESTML-8.2.0.data/data/doc/fig/genn-logo.png
NESTML-8.2.0.data/data/doc/fig/integration_order.pdf
NESTML-8.2.0.data/data/doc/fig/integration_order.png
NESTML-8.2.0.data/data/doc/fig/integration_order_example.png
NESTML-8.2.0.data/data/doc/fig/internal_workflow.png
NESTML-8.2.0.data/data/doc/fig/internal_workflow.svg
NESTML-8.2.0.data/data/doc/fig/nest-desktop.svg
NESTML-8.2.0.data/data/doc/fig/nest-simulator-logo.png
NESTML-8.2.0.data/data/doc/fig/nestml-multisynapse-example.png
NESTML-8.2.0.data/data/doc/fig/nestml_code_render_merged.png
NESTML-8.2.0.data/data/doc/fig/nestml_code_render_thumbnail.png
NESTML-8.2.0.data/data/doc/fig/neuron_illustration.svg
NESTML-8.2.0.data/data/doc/fig/neuron_synapse_co_generation.png
NESTML-8.2.0.data/data/doc/fig/neuron_synapse_co_generation.svg
NESTML-8.2.0.data/data/doc/fig/performance_ratio_nonVec_vs_vec_compartmental.png
NESTML-8.2.0.data/data/doc/fig/python-logo.png
NESTML-8.2.0.data/data/doc/fig/spinnaker_logo.svg
NESTML-8.2.0.data/data/doc/fig/stdp-nearest-neighbour.png
NESTML-8.2.0.data/data/doc/fig/stdp_synapse_test.png
NESTML-8.2.0.data/data/doc/fig/stdp_test_window.png
NESTML-8.2.0.data/data/doc/fig/stdp_triplet_synapse_test.png
NESTML-8.2.0.dist-info/LICENSE
NESTML-8.2.0.dist-info/METADATA
NESTML-8.2.0.dist-info/WHEEL
NESTML-8.2.0.dist-info/entry_points.txt
NESTML-8.2.0.dist-info/top_level.txt
NESTML-8.2.0.dist-info/RECORD
